altcolor/__init__.py
altcolor/altcolor.py
altcolor-0.0.4.dist-info/LICENSE
altcolor-0.0.4.dist-info/METADATA
altcolor-0.0.4.dist-info/WHEEL
altcolor-0.0.4.dist-info/top_level.txt
altcolor-0.0.4.dist-info/RECORD
