Metadata-Version: 2.1
Name: altcolor
Version: 0.0.4
Summary: A package designed to add color to text in console based applications. **[Credit to [colorama]('https://pypi.org/project/colorama/') for a few of the colors]**
Home-page: https://github.com/TaireruLLC/altcolor
Author: Taireru LLC
Author-email: tairerullc@gmail.com
Classifier: Programming Language :: Python :: 3
Classifier: License :: OSI Approved :: MIT License
Classifier: Operating System :: OS Independent
Requires-Python: >=3.6
License-File: LICENSE
Requires-Dist: colorama
